{"root":{"type":"sequence","config":{"type":"sequence","label":{"tag":"TTAB2E","events":{},"title":"普通小鱼主循环 ","group":"composite","name":"Sequence","uuid":"7c895CfOwBCgKYk2gJEdRCX","properties":{},"order":0}},"elements":[],"children":[{"type":"sequence","config":{"type":"sequence","label":{"tag":"TTO1TE","events":{},"title":"移动执行 ","group":"composite","name":"Sequence","uuid":"7c895CfOwBCgKYk2gJEdRCX","properties":{},"order":1}},"elements":[],"children":[{"type":"selector","config":{"type":"selector","label":{"tag":"TT4KAD","events":{},"title":"移动坐标计算逻辑","group":"composite","name":"Selector","uuid":"8a33895bcRHv7EVmZOdpDNK","properties":{},"order":4}},"elements":[{"type":"decorator","config":{"type":"decorator","tag":"U0975X","title":"Conditional","order":2,"events":{"onUpdate":{"node":{"name":"ChaetodonMinimus","path":"/"},"component":{"uuid":"c942fcwHw9F/YDcb/gdd83w","name":"ChaetodonMinimus"},"method":"AlwaysSuccess"}},"group":"decorator","name":"Conditional","uuid":"4d930L3FnhCv71nra+1BGRk","properties":{},"isCondition":true}},{"type":"decorator","config":{"type":"decorator","tag":"U08GIN","title":"ForceSuccessful","order":3,"events":{},"group":"decorator","name":"ForceSuccessful","uuid":"ef4acEffpdO1IBYSHuf4GgQ","properties":{}}}],"children":[{"type":"task","config":{"type":"task","label":{"tag":"U05R20","events":{"onUpdate":{"node":{"name":"ChaetodonMinimus","path":"/"},"component":{"uuid":"c942fcwHw9F/YDcb/gdd83w","name":"ChaetodonMinimus"},"method":"AlwaysFailure"}},"title":"Task","group":"task","name":"Task","uuid":"917dc/B4bBArq1QrBFaQ6gk","properties":{},"order":6}},"elements":[{"type":"decorator","config":{"type":"decorator","tag":"TTG06G","title":"如果当前没有设置移动终点的话","order":5,"events":{"onUpdate":{"node":{"name":"ChaetodonMinimus","path":"/"},"component":{"uuid":"c942fcwHw9F/YDcb/gdd83w","name":"ChaetodonMinimus"},"method":"GetNotSetMovePos"}},"group":"decorator","name":"Conditional","uuid":"4d930L3FnhCv71nra+1BGRk","properties":{},"isCondition":true}}],"children":[]},{"type":"sequence","config":{"type":"sequence","label":{"tag":"TT4V3T","events":{},"title":"新生鱼","group":"composite","name":"Sequence","uuid":"7c895CfOwBCgKYk2gJEdRCX","properties":{},"order":8}},"elements":[{"type":"decorator","config":{"type":"decorator","tag":"TWNZZ4","title":"是否新生鱼","order":7,"events":{"onUpdate":{"node":{"name":"ChaetodonMinimus","path":"/"},"component":{"uuid":"c942fcwHw9F/YDcb/gdd83w","name":"ChaetodonMinimus"},"method":"IsNewFish"}},"group":"decorator","name":"Conditional","uuid":"4d930L3FnhCv71nra+1BGRk","properties":{},"isCondition":true}}],"children":[{"type":"task","config":{"type":"task","label":{"tag":"TWZQYH","events":{"onUpdate":{"node":{"name":"ChaetodonMinimus","path":"/"},"component":{"uuid":"c942fcwHw9F/YDcb/gdd83w","name":"ChaetodonMinimus"},"method":"SetNewFishMovePosition"}},"title":"新生鱼类的移动","group":"task","name":"Task","uuid":"917dc/B4bBArq1QrBFaQ6gk","properties":{},"order":9}},"elements":[],"children":[]}]},{"type":"sequence","config":{"type":"sequence","label":{"tag":"TT4ZE4","events":{},"title":"普通饥饿","group":"composite","name":"Sequence","uuid":"7c895CfOwBCgKYk2gJEdRCX","properties":{},"order":10}},"elements":[],"children":[{"type":"task","config":{"type":"task","label":{"tag":"TXPM4F","events":{"onUpdate":{"node":{"name":"","path":""},"component":{"uuid":"","name":""},"method":""}},"title":"Task","group":"task","name":"Task","uuid":"917dc/B4bBArq1QrBFaQ6gk","properties":{},"order":12}},"elements":[{"type":"decorator","config":{"type":"decorator","tag":"TXPQLZ","title":"ForceFailure","order":11,"events":{},"group":"decorator","name":"ForceFailure","uuid":"0c445cwFwlFJIy1bJtPqjcb","properties":{}}}],"children":[]}]},{"type":"sequence","config":{"type":"sequence","label":{"tag":"TT50K4","events":{},"title":"濒死饥饿","group":"composite","name":"Sequence","uuid":"7c895CfOwBCgKYk2gJEdRCX","properties":{},"order":13}},"elements":[],"children":[{"type":"task","config":{"type":"task","label":{"tag":"TZ7IKP","events":{"onUpdate":{"node":{"name":"","path":""},"component":{"uuid":"","name":""},"method":""}},"title":"Task","group":"task","name":"Task","uuid":"917dc/B4bBArq1QrBFaQ6gk","properties":{},"order":15}},"elements":[{"type":"decorator","config":{"type":"decorator","tag":"TXPQLZ","title":"ForceFailure","order":14,"events":{},"group":"decorator","name":"ForceFailure","uuid":"0c445cwFwlFJIy1bJtPqjcb","properties":{}}}],"children":[]}]},{"type":"sequence","config":{"type":"sequence","label":{"tag":"TUMSRK","events":{},"title":"濒死状态","group":"composite","name":"Sequence","uuid":"7c895CfOwBCgKYk2gJEdRCX","properties":{},"order":16}},"elements":[],"children":[{"type":"task","config":{"type":"task","label":{"tag":"TZ8HRA","events":{"onUpdate":{"node":{"name":"","path":""},"component":{"uuid":"","name":""},"method":""}},"title":"Task","group":"task","name":"Task","uuid":"917dc/B4bBArq1QrBFaQ6gk","properties":{},"order":18}},"elements":[{"type":"decorator","config":{"type":"decorator","tag":"TXPQLZ","title":"ForceFailure","order":17,"events":{},"group":"decorator","name":"ForceFailure","uuid":"0c445cwFwlFJIy1bJtPqjcb","properties":{}}}],"children":[]}]},{"type":"sequence","config":{"type":"sequence","label":{"tag":"TT51CE","events":{},"title":"攻击状态","group":"composite","name":"Sequence","uuid":"7c895CfOwBCgKYk2gJEdRCX","properties":{},"order":19}},"elements":[],"children":[{"type":"task","config":{"type":"task","label":{"tag":"TZ7JYO","events":{"onUpdate":{"node":{"name":"","path":""},"component":{"uuid":"","name":""},"method":""}},"title":"Task","group":"task","name":"Task","uuid":"917dc/B4bBArq1QrBFaQ6gk","properties":{},"order":21}},"elements":[{"type":"decorator","config":{"type":"decorator","tag":"TXPQLZ","title":"ForceFailure","order":20,"events":{},"group":"decorator","name":"ForceFailure","uuid":"0c445cwFwlFJIy1bJtPqjcb","properties":{}}}],"children":[]}]},{"type":"sequence","config":{"type":"sequence","label":{"tag":"TTSZMI","events":{},"title":"普通移动状态","group":"composite","name":"Sequence","uuid":"7c895CfOwBCgKYk2gJEdRCX","properties":{},"order":22}},"elements":[],"children":[{"type":"task","config":{"type":"task","label":{"tag":"TZ8ZOT","events":{"onUpdate":{"node":{"name":"","path":"/"},"component":{"uuid":"c942fcwHw9F/YDcb/gdd83w","name":"ChaetodonMinimus"},"method":""}},"title":"设置随机移动","group":"task","name":"Task","uuid":"917dc/B4bBArq1QrBFaQ6gk","properties":{},"order":23}},"elements":[],"children":[]}]}]},{"type":"sequence","config":{"type":"sequence","label":{"tag":"TY0DYZ","events":{},"title":"移动逻辑","group":"composite","name":"Sequence","uuid":"7c895CfOwBCgKYk2gJEdRCX","properties":{},"order":24}},"elements":[],"children":[{"type":"selector","config":{"type":"selector","label":{"tag":"TY17V6","events":{},"title":"移动逻辑","group":"composite","name":"Selector","uuid":"8a33895bcRHv7EVmZOdpDNK","properties":{},"order":26}},"elements":[{"type":"decorator","config":{"type":"decorator","tag":"TY1R4W","title":"当前移动状态为真","order":25,"events":{"onUpdate":{"node":{"name":"ChaetodonMinimus","path":"/"},"component":{"uuid":"c942fcwHw9F/YDcb/gdd83w","name":"ChaetodonMinimus"},"method":"OwnerMoveStatus"}},"group":"decorator","name":"Conditional","uuid":"4d930L3FnhCv71nra+1BGRk","properties":{},"isCondition":true}}],"children":[{"type":"task","config":{"type":"task","label":{"tag":"TZ7LMT","events":{"onUpdate":{"node":{"name":"ChaetodonMinimus","path":"/"},"component":{"uuid":"c942fcwHw9F/YDcb/gdd83w","name":"ChaetodonMinimus"},"method":"FishStop"}},"title":"停止移动","group":"task","name":"Task","uuid":"917dc/B4bBArq1QrBFaQ6gk","properties":{},"order":28}},"elements":[{"type":"decorator","config":{"type":"decorator","tag":"TZ4PMA","title":"是否很接近目标","order":27,"events":{"onUpdate":{"node":{"name":"ChaetodonMinimus","path":"/"},"component":{"uuid":"c942fcwHw9F/YDcb/gdd83w","name":"ChaetodonMinimus"},"method":"IsArrive"}},"group":"decorator","name":"Conditional","uuid":"4d930L3FnhCv71nra+1BGRk","properties":{},"isCondition":true}}],"children":[]},{"type":"task","config":{"type":"task","label":{"tag":"TZ7P7V","events":{"onUpdate":{"node":{"name":"ChaetodonMinimus","path":"/"},"component":{"uuid":"c942fcwHw9F/YDcb/gdd83w","name":"ChaetodonMinimus"},"method":"FishMove"}},"title":"移动小鱼","group":"task","name":"Task","uuid":"917dc/B4bBArq1QrBFaQ6gk","properties":{},"order":29}},"elements":[],"children":[]}]}]},{"type":"sequence","config":{"type":"sequence","label":{"tag":"TTU5YO","events":{},"title":"检查周身环境状态","group":"composite","name":"Sequence","uuid":"7c895CfOwBCgKYk2gJEdRCX","properties":{},"order":31}},"elements":[{"type":"decorator","config":{"type":"decorator","tag":"TY57FH","title":"Conditional","order":30,"events":{"onUpdate":{"node":{"name":"ChaetodonMinimus","path":"/"},"component":{"uuid":"c942fcwHw9F/YDcb/gdd83w","name":"ChaetodonMinimus"},"method":"AlwaysFailure"}},"group":"decorator","name":"Conditional","uuid":"4d930L3FnhCv71nra+1BGRk","properties":{},"isCondition":true}}],"children":[{"type":"task","config":{"type":"task","label":{"tag":"TTVAEE","events":{"onUpdate":{"node":{"name":"","path":""},"component":{"uuid":"","name":""},"method":""}},"title":"使用道具","group":"task","name":"Task","uuid":"917dc/B4bBArq1QrBFaQ6gk","properties":{},"order":33}},"elements":[{"type":"decorator","config":{"type":"decorator","tag":"TTVGLF","title":"身边有能够使用的道具","order":32,"events":{"onUpdate":{"node":{"name":"","path":""},"component":{"uuid":"","name":""},"method":""}},"group":"decorator","name":"Conditional","uuid":"4d930L3FnhCv71nra+1BGRk","properties":{},"isCondition":true}}],"children":[]},{"type":"task","config":{"type":"task","label":{"tag":"TTW20N","events":{"onUpdate":{"node":{"name":"","path":""},"component":{"uuid":"","name":""},"method":""}},"title":"攻击敌人","group":"task","name":"Task","uuid":"917dc/B4bBArq1QrBFaQ6gk","properties":{},"order":35}},"elements":[{"type":"decorator","config":{"type":"decorator","tag":"TTWJGQ","title":"身边有敌人的话","order":34,"events":{"onUpdate":{"node":{"name":"","path":""},"component":{"uuid":"","name":""},"method":""}},"group":"decorator","name":"Conditional","uuid":"4d930L3FnhCv71nra+1BGRk","properties":{},"isCondition":true}}],"children":[]}]}]}]},"refs":[],"blackboard":{"variables":[{"name":"AAA","tooltip":"asd","value":{"default":0,"TYPE":"bt.SharedNumber"}}],"globals":[]},"runtime":"oreo-behavior-creator","version":"1.1.2","uuid":"18OzCeHIBMSaKwTaOXqBoH"}