{"skeleton":{"hash":"U8bGKo8OUc4+ak9llIkRbDByAX0","spine":"3.8.75","x":-40,"y":-40,"width":80,"height":80},"bones":[{"name":"ButterflyFish"}],"slots":[{"name":"MainTexture","bone":"ButterflyFish","attachment":"smallturn_9"}],"skins":[{"name":"default","attachments":{"MainTexture":{"hungryeat_0":{"width":80,"height":80},"hungryeat_1":{"width":80,"height":80},"hungryeat_2":{"width":80,"height":80},"hungryeat_3":{"width":80,"height":80},"hungryeat_4":{"width":80,"height":80},"hungryeat_5":{"width":80,"height":80},"hungryeat_6":{"width":80,"height":80},"hungryeat_7":{"width":80,"height":80},"hungryeat_8":{"width":80,"height":80},"hungryeat_9":{"width":80,"height":80},"hungryswim_0":{"width":80,"height":80},"hungryswim_1":{"width":80,"height":80},"hungryswim_2":{"width":80,"height":80},"hungryswim_3":{"width":80,"height":80},"hungryswim_4":{"width":80,"height":80},"hungryswim_5":{"width":80,"height":80},"hungryswim_6":{"width":80,"height":80},"hungryswim_7":{"width":80,"height":80},"hungryswim_8":{"width":80,"height":80},"hungryswim_9":{"width":80,"height":80},"hungryturn_0":{"width":80,"height":80},"hungryturn_1":{"width":80,"height":80},"hungryturn_2":{"width":80,"height":80},"hungryturn_3":{"width":80,"height":80},"hungryturn_4":{"width":80,"height":80},"hungryturn_5":{"width":80,"height":80},"hungryturn_6":{"width":80,"height":80},"hungryturn_7":{"width":80,"height":80},"hungryturn_8":{"width":80,"height":80},"hungryturn_9":{"width":80,"height":80},"smalldie_0":{"width":80,"height":80},"smalldie_1":{"width":80,"height":80},"smalldie_2":{"width":80,"height":80},"smalldie_3":{"width":80,"height":80},"smalldie_4":{"width":80,"height":80},"smalldie_5":{"width":80,"height":80},"smalldie_6":{"width":80,"height":80},"smalldie_7":{"width":80,"height":80},"smalldie_8":{"width":80,"height":80},"smalldie_9":{"width":80,"height":80},"smalleat_0":{"width":80,"height":80},"smalleat_1":{"width":80,"height":80},"smalleat_2":{"width":80,"height":80},"smalleat_3":{"width":80,"height":80},"smalleat_4":{"width":80,"height":80},"smalleat_5":{"width":80,"height":80},"smalleat_6":{"width":80,"height":80},"smalleat_7":{"width":80,"height":80},"smalleat_8":{"width":80,"height":80},"smalleat_9":{"width":80,"height":80},"smallswim_0":{"width":80,"height":80},"smallswim_1":{"width":80,"height":80},"smallswim_2":{"width":80,"height":80},"smallswim_3":{"width":80,"height":80},"smallswim_4":{"width":80,"height":80},"smallswim_5":{"width":80,"height":80},"smallswim_6":{"width":80,"height":80},"smallswim_7":{"width":80,"height":80},"smallswim_8":{"width":80,"height":80},"smallswim_9":{"width":80,"height":80},"smallturn_0":{"width":80,"height":80},"smallturn_1":{"width":80,"height":80},"smallturn_2":{"width":80,"height":80},"smallturn_3":{"width":80,"height":80},"smallturn_4":{"width":80,"height":80},"smallturn_5":{"width":80,"height":80},"smallturn_6":{"width":80,"height":80},"smallturn_7":{"width":80,"height":80},"smallturn_8":{"width":80,"height":80},"smallturn_9":{"width":80,"height":80}}}}],"animations":{"Die_Left":{"slots":{"MainTexture":{"attachment":[{"name":"smalldie_0"},{"time":0.1,"name":"smalldie_1"},{"time":0.2,"name":"smalldie_2"},{"time":0.3,"name":"smalldie_3"},{"time":0.4,"name":"smalldie_4"},{"time":0.5,"name":"smalldie_5"},{"time":0.6,"name":"smalldie_6"},{"time":0.7,"name":"smalldie_7"},{"time":0.8,"name":"smalldie_8"},{"time":0.9,"name":"smalldie_9"}]}}},"Die_Right":{"slots":{"MainTexture":{"attachment":[{"name":"smalldie_0"},{"time":0.1,"name":"smalldie_1"},{"time":0.2,"name":"smalldie_2"},{"time":0.3,"name":"smalldie_3"},{"time":0.4,"name":"smalldie_4"},{"time":0.5,"name":"smalldie_5"},{"time":0.6,"name":"smalldie_6"},{"time":0.7,"name":"smalldie_7"},{"time":0.8,"name":"smalldie_8"},{"time":0.9,"name":"smalldie_9"}]}},"bones":{"ButterflyFish":{"scale":[{"x":-1}]}}},"HungryEat_Left":{"slots":{"MainTexture":{"attachment":[{"name":"hungryeat_0"},{"time":0.1,"name":"hungryeat_1"},{"time":0.2,"name":"hungryeat_2"},{"time":0.3,"name":"hungryeat_3"},{"time":0.4,"name":"hungryeat_4"},{"time":0.5,"name":"hungryeat_5"},{"time":0.6,"name":"hungryeat_6"},{"time":0.7,"name":"hungryeat_7"},{"time":0.8,"name":"hungryeat_8"},{"time":0.9,"name":"hungryeat_9"}]}}},"HungryEat_Right":{"slots":{"MainTexture":{"attachment":[{"name":"hungryeat_0"},{"time":0.1,"name":"hungryeat_1"},{"time":0.2,"name":"hungryeat_2"},{"time":0.3,"name":"hungryeat_3"},{"time":0.4,"name":"hungryeat_4"},{"time":0.5,"name":"hungryeat_5"},{"time":0.6,"name":"hungryeat_6"},{"time":0.7,"name":"hungryeat_7"},{"time":0.8,"name":"hungryeat_8"},{"time":0.9,"name":"hungryeat_9"}]}},"bones":{"ButterflyFish":{"scale":[{"x":-1}]}}},"HungrySwim_Left":{"slots":{"MainTexture":{"attachment":[{"name":"hungryswim_0"},{"time":0.1,"name":"hungryswim_1"},{"time":0.2,"name":"hungryswim_2"},{"time":0.3,"name":"hungryswim_3"},{"time":0.4,"name":"hungryswim_4"},{"time":0.5,"name":"hungryswim_5"},{"time":0.6,"name":"hungryswim_6"},{"time":0.7,"name":"hungryswim_7"},{"time":0.8,"name":"hungryswim_8"},{"time":0.9,"name":"hungryswim_9"},{"time":1,"name":"hungryswim_9"}]}}},"HungrySwim_Right":{"slots":{"MainTexture":{"attachment":[{"name":"hungryswim_0"},{"time":0.1,"name":"hungryswim_1"},{"time":0.2,"name":"hungryswim_2"},{"time":0.3,"name":"hungryswim_3"},{"time":0.4,"name":"hungryswim_4"},{"time":0.5,"name":"hungryswim_5"},{"time":0.6,"name":"hungryswim_6"},{"time":0.7,"name":"hungryswim_7"},{"time":0.8,"name":"hungryswim_8"},{"time":0.9,"name":"hungryswim_9"},{"time":1,"name":"hungryswim_9"}]}},"bones":{"ButterflyFish":{"scale":[{"x":-1}]}}},"HungryTurn_Left":{"slots":{"MainTexture":{"attachment":[{"name":"hungryturn_0"},{"time":0.1,"name":"hungryturn_1"},{"time":0.2,"name":"hungryturn_2"},{"time":0.3,"name":"hungryturn_3"},{"time":0.4,"name":"hungryturn_4"},{"time":0.5,"name":"hungryturn_5"},{"time":0.6,"name":"hungryturn_6"},{"time":0.7,"name":"hungryturn_7"},{"time":0.8,"name":"hungryturn_8"},{"time":0.9,"name":"hungryturn_9"}]}},"bones":{"ButterflyFish":{"scale":[{"x":-1}]}}},"HungryTurn_Right":{"slots":{"MainTexture":{"attachment":[{"name":"hungryturn_0"},{"time":0.1,"name":"hungryturn_1"},{"time":0.2,"name":"hungryturn_2"},{"time":0.3,"name":"hungryturn_3"},{"time":0.4,"name":"hungryturn_4"},{"time":0.5,"name":"hungryturn_5"},{"time":0.6,"name":"hungryturn_6"},{"time":0.7,"name":"hungryturn_7"},{"time":0.8,"name":"hungryturn_8"},{"time":0.9,"name":"hungryturn_9"}]}}},"NoramlEat_Left":{"slots":{"MainTexture":{"attachment":[{"name":"smalleat_0"},{"time":0.1,"name":"smalleat_1"},{"time":0.2,"name":"smalleat_2"},{"time":0.3,"name":"smalleat_3"},{"time":0.4,"name":"smalleat_4"},{"time":0.5,"name":"smalleat_5"},{"time":0.6,"name":"smalleat_6"},{"time":0.7,"name":"smalleat_7"},{"time":0.8,"name":"smalleat_8"},{"time":0.9,"name":"smalleat_9"}]}}},"NoramlEat_Right":{"slots":{"MainTexture":{"attachment":[{"name":"smalleat_0"},{"time":0.1,"name":"smalleat_1"},{"time":0.2,"name":"smalleat_2"},{"time":0.3,"name":"smalleat_3"},{"time":0.4,"name":"smalleat_4"},{"time":0.5,"name":"smalleat_5"},{"time":0.6,"name":"smalleat_6"},{"time":0.7,"name":"smalleat_7"},{"time":0.8,"name":"smalleat_8"},{"time":0.9,"name":"smalleat_9"}]}},"bones":{"ButterflyFish":{"scale":[{"x":-1}]}}},"NormalTurn_Left":{"slots":{"MainTexture":{"attachment":[{"name":"smallturn_0"},{"time":0.0333,"name":"smallturn_1"},{"time":0.0667,"name":"smallturn_2"},{"time":0.1,"name":"smallturn_3"},{"time":0.1333,"name":"smallturn_4"},{"time":0.2,"name":"smallturn_5"},{"time":0.2667,"name":"smallturn_6"},{"time":0.3333,"name":"smallturn_7"},{"time":0.4,"name":"smallturn_8"},{"time":0.4667,"name":"smallturn_9"}]}},"bones":{"ButterflyFish":{"scale":[{"x":-1}]}}},"NormalTurn_Right":{"slots":{"MainTexture":{"attachment":[{"name":"smallturn_0"},{"time":0.0333,"name":"smallturn_1"},{"time":0.0667,"name":"smallturn_2"},{"time":0.1,"name":"smallturn_3"},{"time":0.1333,"name":"smallturn_4"},{"time":0.1667,"name":"smallturn_5"},{"time":0.2333,"name":"smallturn_6"},{"time":0.3,"name":"smallturn_7"},{"time":0.3667,"name":"smallturn_8"},{"time":0.4333,"name":"smallturn_9"}]}}},"SwimNormal_Left":{"slots":{"MainTexture":{"attachment":[{"name":"smallswim_0"},{"time":0.1,"name":"smallswim_1"},{"time":0.2,"name":"smallswim_2"},{"time":0.3,"name":"smallswim_3"},{"time":0.4,"name":"smallswim_4"},{"time":0.5,"name":"smallswim_5"},{"time":0.6,"name":"smallswim_6"},{"time":0.7,"name":"smallswim_7"},{"time":0.8,"name":"smallswim_8"},{"time":0.9,"name":"smallswim_9"},{"time":1,"name":"smallswim_9"}]}}},"SwimNormal_Right":{"slots":{"MainTexture":{"attachment":[{"name":"smallswim_0"},{"time":0.1,"name":"smallswim_1"},{"time":0.2,"name":"smallswim_2"},{"time":0.3,"name":"smallswim_3"},{"time":0.4,"name":"smallswim_4"},{"time":0.5,"name":"smallswim_5"},{"time":0.6,"name":"smallswim_6"},{"time":0.7,"name":"smallswim_7"},{"time":0.8,"name":"smallswim_8"},{"time":0.9,"name":"smallswim_9"},{"time":1,"name":"smallswim_9"}]}},"bones":{"ButterflyFish":{"scale":[{"x":-1}]}}}}}